twarc_divide.py
twarc_divide-0.1.0.dist-info/LICENSE
twarc_divide-0.1.0.dist-info/METADATA
twarc_divide-0.1.0.dist-info/WHEEL
twarc_divide-0.1.0.dist-info/entry_points.txt
twarc_divide-0.1.0.dist-info/top_level.txt
twarc_divide-0.1.0.dist-info/RECORD
