Metadata-Version: 2.1
Name: twarc-divide
Version: 0.1.0
Home-page: https://github.com/JoanMassachs/twarc-divide
Author: Joan Massachs
License: Apache Software License 2.0 (Apache-2.0)
Classifier: License :: OSI Approved :: Apache Software License
Requires-Python: >=3.6
License-File: LICENSE
Requires-Dist: twarc
